{"nodes": [{"id": "src_app_api_properties_propertyid_route_ts", "label": "route.ts", "file_type": "code", "source_file": "src\\app\\api\\properties\\[propertyId]\\route.ts", "source_location": "L1"}, {"id": "route_canmanageproperty", "label": "canManageProperty()", "file_type": "code", "source_file": "src\\app\\api\\properties\\[propertyId]\\route.ts", "source_location": "L10"}, {"id": "route_get", "label": "GET()", "file_type": "code", "source_file": "src\\app\\api\\properties\\[propertyId]\\route.ts", "source_location": "L15"}, {"id": "route_patch", "label": "PATCH()", "file_type": "code", "source_file": "src\\app\\api\\properties\\[propertyId]\\route.ts", "source_location": "L53"}, {"id": "route_delete", "label": "DELETE()", "file_type": "code", "source_file": "src\\app\\api\\properties\\[propertyId]\\route.ts", "source_location": "L93"}], "edges": [{"source": "src_app_api_properties_propertyid_route_ts", "target": "server", "relation": "imports_from", "confidence": "EXTRACTED", "source_file": "src\\app\\api\\properties\\[propertyId]\\route.ts", "source_location": "L1", "weight": 1.0}, {"source": "src_app_api_properties_propertyid_route_ts", "target": "next_auth", "relation": "imports_from", "confidence": "EXTRACTED", "source_file": "src\\app\\api\\properties\\[propertyId]\\route.ts", "source_location": "L2", "weight": 1.0}, {"source": "src_app_api_properties_propertyid_route_ts", "target": "db", "relation": "imports_from", "confidence": "EXTRACTED", "source_file": "src\\app\\api\\properties\\[propertyId]\\route.ts", "source_location": "L4", "weight": 1.0}, {"source": "src_app_api_properties_propertyid_route_ts", "target": "auth_options", "relation": "imports_from", "confidence": "EXTRACTED", "source_file": "src\\app\\api\\properties\\[propertyId]\\route.ts", "source_location": "L5", "weight": 1.0}, {"source": "src_app_api_properties_propertyid_route_ts", "target": "property", "relation": "imports_from", "confidence": "EXTRACTED", "source_file": "src\\app\\api\\properties\\[propertyId]\\route.ts", "source_location": "L6", "weight": 1.0}, {"source": "src_app_api_properties_propertyid_route_ts", "target": "next_auth", "relation": "imports_from", "confidence": "EXTRACTED", "source_file": "src\\app\\api\\properties\\[propertyId]\\route.ts", "source_location": "L7", "weight": 1.0}, {"source": "src_app_api_properties_propertyid_route_ts", "target": "route_canmanageproperty", "relation": "contains", "confidence": "EXTRACTED", "source_file": "src\\app\\api\\properties\\[propertyId]\\route.ts", "source_location": "L10", "weight": 1.0}, {"source": "src_app_api_properties_propertyid_route_ts", "target": "route_get", "relation": "contains", "confidence": "EXTRACTED", "source_file": "src\\app\\api\\properties\\[propertyId]\\route.ts", "source_location": "L15", "weight": 1.0}, {"source": "src_app_api_properties_propertyid_route_ts", "target": "route_patch", "relation": "contains", "confidence": "EXTRACTED", "source_file": "src\\app\\api\\properties\\[propertyId]\\route.ts", "source_location": "L53", "weight": 1.0}, {"source": "src_app_api_properties_propertyid_route_ts", "target": "route_delete", "relation": "contains", "confidence": "EXTRACTED", "source_file": "src\\app\\api\\properties\\[propertyId]\\route.ts", "source_location": "L93", "weight": 1.0}, {"source": "route_patch", "target": "route_canmanageproperty", "relation": "calls", "confidence": "EXTRACTED", "source_file": "src\\app\\api\\properties\\[propertyId]\\route.ts", "source_location": "L73", "weight": 1.0}, {"source": "route_delete", "target": "route_canmanageproperty", "relation": "calls", "confidence": "EXTRACTED", "source_file": "src\\app\\api\\properties\\[propertyId]\\route.ts", "source_location": "L113", "weight": 1.0}]}